[{"Interactions": 23996, "Engagements": 15331, "Video played to 75%": 11.0, "Avg. position": 1.0, "Unique cookies": "", "Impressions": 131886, "Campaign": "ZTM | 1707020 1708033 1709018 | UAC iOS", "Account ID": "9021114325", "Campaign ID": 871735807, "Account Name": "VNG - PG1 - ZTM", "Campaign serving status": "eligible", "Mapping": false, "Bid Strategy Type": "Target CPA", "Avg. CPV": 0.008886, "Video played to 25%": 20.48, "Views": 17424, "Avg. CPM": 1.337638, "Interaction Types": ["Clicks", "Engagements", "Views"], "Campaign state": "paused", "End date": "", "Video played to 50%": 14.42, "Interaction Rate": 18.19, "Advertising Channel": "Multi Channel", "CTR": 0.56, "Advertising Sub Channel": "Universal App Campaign", "Avg. CPE": 0.010245, "Date": "2017-08-07", "Conversions": 54.0, "Avg. Cost": 0.007352, "Invalid clicks": 56, "Clicks": 741, "Avg. CPC": 0.238078, "Cost": 176.41568, "Video played to 100%": 6.04, "View rate": 17.86, "Start date": "2017-07-02"}, {"Interactions": 266, "Engagements": 0, "Video played to 75%": 0.0, "Avg. position": 1.9, "Unique cookies": "", "Impressions": 4124, "Campaign": "ZTM | 1707020 1708033 1709018 | Search Play Store", "Account ID": "9021114325", "Campaign ID": 872428791, "Account Name": "VNG - PG1 - ZTM", "Campaign serving status": "eligible", "Mapping": false, "Bid Strategy Type": "Target CPA", "Avg. CPV": 0.0, "Video played to 25%": 0.0, "Views": 0, "Avg. CPM": 5.080019, "Interaction Types": ["Clicks"], "Campaign state": "enabled", "End date": "", "Video played to 50%": 0.0, "Interaction Rate": 6.45, "Advertising Channel": "Search", "CTR": 6.45, "Advertising Sub Channel": "Search Mobile App", "Avg. CPE": 0.0, "Date": "2017-08-07", "Conversions": 85.0, "Avg. Cost": 0.078759, "Invalid clicks": 24, "Clicks": 266, "Avg. CPC": 0.078759, "Cost": 20.95, "Video played to 100%": 0.0, "View rate": 0.0, "Start date": "2017-07-01"}, {"Interactions": 5223, "Engagements": 1355, "Video played to 75%": 26.66, "Avg. position": 1.2, "Unique cookies": "", "Impressions": 154573, "Campaign": "ZTM | 1707020 1708033 1709018 | UAC Android", "Account ID": "9021114325", "Campaign ID": 872427837, "Account Name": "VNG - PG1 - ZTM", "Campaign serving status": "eligible", "Mapping": false, "Bid Strategy Type": "Target CPA", "Avg. CPV": 0.005241, "Video played to 25%": 33.96, "Views": 1203, "Avg. CPM": 1.303943, "Interaction Types": ["Clicks", "Engagements", "Views"], "Campaign state": "enabled", "End date": "", "Video played to 50%": 29.52, "Interaction Rate": 3.38, "Advertising Channel": "Multi Channel", "CTR": 2.3, "Advertising Sub Channel": "Universal App Campaign", "Avg. CPE": 0.005125, "Date": "2017-08-07", "Conversions": 132.0, "Avg. Cost": 0.03859, "Invalid clicks": 574, "Clicks": 3553, "Avg. CPC": 0.056728, "Cost": 201.55445, "Video played to 100%": 22.43, "View rate": 24.73, "Start date": "2017-07-01"}, {"Interactions": 1034, "Engagements": 0, "Video played to 75%": 0.0, "Avg. position": 2.9, "Unique cookies": "", "Impressions": 9416, "Campaign": "ZTM | 1706071 1707018 1708032 1709021 | SEM", "Account ID": "9021114325", "Campaign ID": 859774457, "Account Name": "VNG - PG1 - ZTM", "Campaign serving status": "eligible", "Mapping": false, "Bid Strategy Type": "cpc", "Avg. CPV": 0.0, "Video played to 25%": 0.0, "Views": 0, "Avg. CPM": 5.591546, "Interaction Types": ["Clicks"], "Campaign state": "enabled", "End date": "", "Video played to 50%": 0.0, "Interaction Rate": 10.98, "Advertising Channel": "Search", "CTR": 10.98, "Advertising Sub Channel": "", "Avg. CPE": 0.0, "Date": "2017-08-07", "Conversions": 14.0, "Avg. Cost": 0.050919, "Invalid clicks": 41, "Clicks": 1034, "Avg. CPC": 0.050919, "Cost": 52.65, "Video played to 100%": 0.0, "View rate": 0.0, "Start date": "2017-06-19"}, {"Interactions": 30519, "Engagements": 16686, "Video played to 75%": 13.04, "Avg. position": 1.2, "Unique cookies": "", "Impressions": 299999, "Campaign": "", "Account ID": "9021114325", "Campaign ID": "", "Account Name": "VNG - PG1 - ZTM", "Campaign serving status": "", "Mapping": false, "Bid Strategy Type": "", "Avg. CPV": 0.00865, "Video played to 25%": 22.24, "Views": 18627, "Avg. CPM": 1.505239, "Interaction Types": "", "Campaign state": "Total", "End date": "", "Video played to 50%": 16.39, "Interaction Rate": 10.17, "Advertising Channel": "", "CTR": 1.86, "Advertising Sub Channel": "", "Avg. CPE": 0.009829, "Date": "2017-08-07", "Conversions": 285.0, "Avg. Cost": 0.014796, "Invalid clicks": 695, "Clicks": 5594, "Avg. CPC": 0.080724, "Cost": 451.57013, "Video played to 100%": 8.18, "View rate": 18.19, "Start date": ""}]