[{"Advertising Sub Channel": "", "Avg. position": 1.2, "Mapping": false, "Conversions": 1.0, "Avg. CPV": 0.0, "CTR": 17.65, "Video played to 25%": 0.0, "Start date": "2017-05-04", "Interactions": 3, "Interaction Rate": 17.65, "Avg. CPE": 0.0, "Avg. Cost": 0.01, "Campaign ID": 819467013, "Avg. CPC": 0.01, "Interaction Types": ["Clicks"], "Account Name": "[W] G1 - WPL - vltkw360", "Engagements": 0, "Date": "2017-08-09", "Advertising Channel": "Search", "Campaign state": "enabled", "Video played to 100%": 0.0, "Avg. CPM": 1.764706, "Bid Strategy Type": "cpc", "Clicks": 3, "Cost": 0.03, "Campaign serving status": "eligible", "Invalid clicks": 0, "Impressions": 17, "Video played to 50%": 0.0, "End date": "", "Video played to 75%": 0.0, "View rate": 0.0, "Unique cookies": "", "Views": 0, "Account ID": "5993679244", "Campaign": "Brand-term_BM_webgame-vo-lam-truyen-ky"}, {"Advertising Sub Channel": "", "Avg. position": 1.5, "Mapping": false, "Conversions": 5.0, "Avg. CPV": 0.0, "CTR": 38.55, "Video played to 25%": 0.0, "Start date": "2017-05-04", "Interactions": 96, "Interaction Rate": 38.55, "Avg. CPE": 0.0, "Avg. Cost": 0.036354, "Campaign ID": 819467190, "Avg. CPC": 0.036354, "Interaction Types": ["Clicks"], "Account Name": "[W] G1 - WPL - vltkw360", "Engagements": 0, "Date": "2017-08-09", "Advertising Channel": "Search", "Campaign state": "enabled", "Video played to 100%": 0.0, "Avg. CPM": 14.016064, "Bid Strategy Type": "cpc", "Clicks": 96, "Cost": 3.49, "Campaign serving status": "eligible", "Invalid clicks": 10, "Impressions": 249, "Video played to 50%": 0.0, "End date": "", "Video played to 75%": 0.0, "View rate": 0.0, "Unique cookies": "", "Views": 0, "Account ID": "5993679244", "Campaign": "Brand-term_PM_vo-lam-truyen-ky"}, {"Advertising Sub Channel": "", "Avg. position": 2.0, "Mapping": false, "Conversions": 0.0, "Avg. CPV": 0.0, "CTR": 50.0, "Video played to 25%": 0.0, "Start date": "2017-05-04", "Interactions": 2, "Interaction Rate": 50.0, "Avg. CPE": 0.0, "Avg. Cost": 0.05, "Campaign ID": 819467223, "Avg. CPC": 0.05, "Interaction Types": ["Clicks"], "Account Name": "[W] G1 - WPL - vltkw360", "Engagements": 0, "Date": "2017-08-09", "Advertising Channel": "Search", "Campaign state": "enabled", "Video played to 100%": 0.0, "Avg. CPM": 25.0, "Bid Strategy Type": "cpc", "Clicks": 2, "Cost": 0.1, "Campaign serving status": "eligible", "Invalid clicks": 0, "Impressions": 4, "Video played to 50%": 0.0, "End date": "", "Video played to 75%": 0.0, "View rate": 0.0, "Unique cookies": "", "Views": 0, "Account ID": "5993679244", "Campaign": "Brand-term_EX_dang-ky-vo-lam"}, {"Advertising Sub Channel": "", "Avg. position": 1.1, "Mapping": false, "Conversions": 34.0, "Avg. CPV": 0.0, "CTR": 57.8, "Video played to 25%": 0.0, "Start date": "2017-05-04", "Interactions": 263, "Interaction Rate": 57.8, "Avg. CPE": 0.0, "Avg. Cost": 0.020228, "Campaign ID": 819466998, "Avg. CPC": 0.020228, "Interaction Types": ["Clicks"], "Account Name": "[W] G1 - WPL - vltkw360", "Engagements": 0, "Date": "2017-08-09", "Advertising Channel": "Search", "Campaign state": "enabled", "Video played to 100%": 0.0, "Avg. CPM": 11.692308, "Bid Strategy Type": "cpc", "Clicks": 263, "Cost": 5.32, "Campaign serving status": "eligible", "Invalid clicks": 12, "Impressions": 455, "Video played to 50%": 0.0, "End date": "", "Video played to 75%": 0.0, "View rate": 0.0, "Unique cookies": "", "Views": 0, "Account ID": "5993679244", "Campaign": "Brand-term_BM_tai-vo-lam"}, {"Advertising Sub Channel": "", "Avg. position": 1.1, "Mapping": false, "Conversions": 1.0, "Avg. CPV": 0.0, "CTR": 66.67, "Video played to 25%": 0.0, "Start date": "2017-05-04", "Interactions": 6, "Interaction Rate": 66.67, "Avg. CPE": 0.0, "Avg. Cost": 0.066667, "Campaign ID": 819467169, "Avg. CPC": 0.066667, "Interaction Types": ["Clicks"], "Account Name": "[W] G1 - WPL - vltkw360", "Engagements": 0, "Date": "2017-08-09", "Advertising Channel": "Search", "Campaign state": "enabled", "Video played to 100%": 0.0, "Avg. CPM": 44.444444, "Bid Strategy Type": "cpc", "Clicks": 6, "Cost": 0.4, "Campaign serving status": "eligible", "Invalid clicks": 0, "Impressions": 9, "Video played to 50%": 0.0, "End date": "", "Video played to 75%": 0.0, "View rate": 0.0, "Unique cookies": "", "Views": 0, "Account ID": "5993679244", "Campaign": "Brand-term_PM_down-vo-lam"}, {"Advertising Sub Channel": "", "Avg. position": 1.3, "Mapping": false, "Conversions": 0.0, "Avg. CPV": 0.0, "CTR": 14.29, "Video played to 25%": 0.0, "Start date": "2017-05-04", "Interactions": 1, "Interaction Rate": 14.29, "Avg. CPE": 0.0, "Avg. Cost": 0.04, "Campaign ID": 819467175, "Avg. CPC": 0.04, "Interaction Types": ["Clicks"], "Account Name": "[W] G1 - WPL - vltkw360", "Engagements": 0, "Date": "2017-08-09", "Advertising Channel": "Search", "Campaign state": "enabled", "Video played to 100%": 0.0, "Avg. CPM": 5.714286, "Bid Strategy Type": "cpc", "Clicks": 1, "Cost": 0.04, "Campaign serving status": "eligible", "Invalid clicks": 0, "Impressions": 7, "Video played to 50%": 0.0, "End date": "", "Video played to 75%": 0.0, "View rate": 0.0, "Unique cookies": "", "Views": 0, "Account ID": "5993679244", "Campaign": "Brand-term_PM_game-vo-lam"}, {"Advertising Sub Channel": "", "Avg. position": 1.4, "Mapping": false, "Conversions": 0.0, "Avg. CPV": 0.0, "CTR": 36.36, "Video played to 25%": 0.0, "Start date": "2017-05-04", "Interactions": 4, "Interaction Rate": 36.36, "Avg. CPE": 0.0, "Avg. Cost": 0.01, "Campaign ID": 819467178, "Avg. CPC": 0.01, "Interaction Types": ["Clicks"], "Account Name": "[W] G1 - WPL - vltkw360", "Engagements": 0, "Date": "2017-08-09", "Advertising Channel": "Search", "Campaign state": "enabled", "Video played to 100%": 0.0, "Avg. CPM": 3.636364, "Bid Strategy Type": "cpc", "Clicks": 4, "Cost": 0.04, "Campaign serving status": "eligible", "Invalid clicks": 1, "Impressions": 11, "Video played to 50%": 0.0, "End date": "", "Video played to 75%": 0.0, "View rate": 0.0, "Unique cookies": "", "Views": 0, "Account ID": "5993679244", "Campaign": "Brand-term_PM_tai-vo-lam"}, {"Advertising Sub Channel": "", "Avg. position": 1.1, "Mapping": false, "Conversions": 3.0, "Avg. CPV": 0.0, "CTR": 17.95, "Video played to 25%": 0.0, "Start date": "2017-05-04", "Interactions": 7, "Interaction Rate": 17.95, "Avg. CPE": 0.0, "Avg. Cost": 0.03, "Campaign ID": 819467022, "Avg. CPC": 0.03, "Interaction Types": ["Clicks"], "Account Name": "[W] G1 - WPL - vltkw360", "Engagements": 0, "Date": "2017-08-09", "Advertising Channel": "Search", "Campaign state": "enabled", "Video played to 100%": 0.0, "Avg. CPM": 5.384615, "Bid Strategy Type": "cpc", "Clicks": 7, "Cost": 0.21, "Campaign serving status": "eligible", "Invalid clicks": 0, "Impressions": 39, "Video played to 50%": 0.0, "End date": "", "Video played to 75%": 0.0, "View rate": 0.0, "Unique cookies": "", "Views": 0, "Account ID": "5993679244", "Campaign": "Brand-term_BM_webgame-vltk"}, {"Advertising Sub Channel": "", "Avg. position": 1.5, "Mapping": false, "Conversions": 1.0, "Avg. CPV": 0.0, "CTR": 59.26, "Video played to 25%": 0.0, "Start date": "2017-05-04", "Interactions": 32, "Interaction Rate": 59.26, "Avg. CPE": 0.0, "Avg. Cost": 0.024063, "Campaign ID": 819467181, "Avg. CPC": 0.024063, "Interaction Types": ["Clicks"], "Account Name": "[W] G1 - WPL - vltkw360", "Engagements": 0, "Date": "2017-08-09", "Advertising Channel": "Search", "Campaign state": "enabled", "Video played to 100%": 0.0, "Avg. CPM": 14.259259, "Bid Strategy Type": "cpc", "Clicks": 32, "Cost": 0.77, "Campaign serving status": "eligible", "Invalid clicks": 0, "Impressions": 54, "Video played to 50%": 0.0, "End date": "", "Video played to 75%": 0.0, "View rate": 0.0, "Unique cookies": "", "Views": 0, "Account ID": "5993679244", "Campaign": "Brand-term_PM_vltk"}, {"Advertising Sub Channel": "", "Avg. position": 1.0, "Mapping": false, "Conversions": 0.0, "Avg. CPV": 0.0, "CTR": 100.0, "Video played to 25%": 0.0, "Start date": "2017-05-04", "Interactions": 3, "Interaction Rate": 100.0, "Avg. CPE": 0.0, "Avg. Cost": 0.01, "Campaign ID": 819467250, "Avg. CPC": 0.01, "Interaction Types": ["Clicks"], "Account Name": "[W] G1 - WPL - vltkw360", "Engagements": 0, "Date": "2017-08-09", "Advertising Channel": "Search", "Campaign state": "enabled", "Video played to 100%": 0.0, "Avg. CPM": 10.0, "Bid Strategy Type": "cpc", "Clicks": 3, "Cost": 0.03, "Campaign serving status": "eligible", "Invalid clicks": 0, "Impressions": 3, "Video played to 50%": 0.0, "End date": "", "Video played to 75%": 0.0, "View rate": 0.0, "Unique cookies": "", "Views": 0, "Account ID": "5993679244", "Campaign": "Brand-term_EX_web-game-vltk"}, {"Advertising Sub Channel": "", "Avg. position": 1.3, "Mapping": false, "Conversions": 2.0, "Avg. CPV": 0.0, "CTR": 69.7, "Video played to 25%": 0.0, "Start date": "2017-05-04", "Interactions": 23, "Interaction Rate": 69.7, "Avg. CPE": 0.0, "Avg. Cost": 0.015217, "Campaign ID": 819467253, "Avg. CPC": 0.015217, "Interaction Types": ["Clicks"], "Account Name": "[W] G1 - WPL - vltkw360", "Engagements": 0, "Date": "2017-08-09", "Advertising Channel": "Search", "Campaign state": "enabled", "Video played to 100%": 0.0, "Avg. CPM": 10.606061, "Bid Strategy Type": "cpc", "Clicks": 23, "Cost": 0.35, "Campaign serving status": "eligible", "Invalid clicks": 1, "Impressions": 33, "Video played to 50%": 0.0, "End date": "", "Video played to 75%": 0.0, "View rate": 0.0, "Unique cookies": "", "Views": 0, "Account ID": "5993679244", "Campaign": "Brand-term_EX_web-game-vo-lam-truyen-ky"}, {"Advertising Sub Channel": "", "Avg. position": 1.2, "Mapping": false, "Conversions": 19.0, "Avg. CPV": 0.0, "CTR": 52.68, "Video played to 25%": 0.0, "Start date": "2017-05-04", "Interactions": 511, "Interaction Rate": 52.68, "Avg. CPE": 0.0, "Avg. Cost": 0.013542, "Campaign ID": 819467004, "Avg. CPC": 0.013542, "Interaction Types": ["Clicks"], "Account Name": "[W] G1 - WPL - vltkw360", "Engagements": 0, "Date": "2017-08-09", "Advertising Channel": "Search", "Campaign state": "enabled", "Video played to 100%": 0.0, "Avg. CPM": 7.134021, "Bid Strategy Type": "cpc", "Clicks": 511, "Cost": 6.92, "Campaign serving status": "eligible", "Invalid clicks": 30, "Impressions": 970, "Video played to 50%": 0.0, "End date": "", "Video played to 75%": 0.0, "View rate": 0.0, "Unique cookies": "", "Views": 0, "Account ID": "5993679244", "Campaign": "Brand-term_BM_vo-lam"}, {"Advertising Sub Channel": "", "Avg. position": 1.7, "Mapping": false, "Conversions": 2.0, "Avg. CPV": 0.0, "CTR": 40.0, "Video played to 25%": 0.0, "Start date": "2017-05-04", "Interactions": 10, "Interaction Rate": 40.0, "Avg. CPE": 0.0, "Avg. Cost": 0.026, "Campaign ID": 819467025, "Avg. CPC": 0.026, "Interaction Types": ["Clicks"], "Account Name": "[W] G1 - WPL - vltkw360", "Engagements": 0, "Date": "2017-08-09", "Advertising Channel": "Search", "Campaign state": "enabled", "Video played to 100%": 0.0, "Avg. CPM": 10.4, "Bid Strategy Type": "cpc", "Clicks": 10, "Cost": 0.26, "Campaign serving status": "eligible", "Invalid clicks": 2, "Impressions": 25, "Video played to 50%": 0.0, "End date": "", "Video played to 75%": 0.0, "View rate": 0.0, "Unique cookies": "", "Views": 0, "Account ID": "5993679244", "Campaign": "Brand-term_BM_360-vo-lam-truyen-ky"}, {"Advertising Sub Channel": "", "Avg. position": 1.7, "Mapping": false, "Conversions": 0.0, "Avg. CPV": 0.0, "CTR": 81.82, "Video played to 25%": 0.0, "Start date": "2017-05-04", "Interactions": 9, "Interaction Rate": 81.82, "Avg. CPE": 0.0, "Avg. Cost": 0.015556, "Campaign ID": 819467208, "Avg. CPC": 0.015556, "Interaction Types": ["Clicks"], "Account Name": "[W] G1 - WPL - vltkw360", "Engagements": 0, "Date": "2017-08-09", "Advertising Channel": "Search", "Campaign state": "enabled", "Video played to 100%": 0.0, "Avg. CPM": 12.727273, "Bid Strategy Type": "cpc", "Clicks": 9, "Cost": 0.14, "Campaign serving status": "eligible", "Invalid clicks": 0, "Impressions": 11, "Video played to 50%": 0.0, "End date": "", "Video played to 75%": 0.0, "View rate": 0.0, "Unique cookies": "", "Views": 0, "Account ID": "5993679244", "Campaign": "Brand-term_PM_webgame-vo-lam-truyen-ky"}, {"Advertising Sub Channel": "", "Avg. position": 1.0, "Mapping": false, "Conversions": 0.0, "Avg. CPV": 0.0, "CTR": 60.0, "Video played to 25%": 0.0, "Start date": "2017-05-04", "Interactions": 3, "Interaction Rate": 60.0, "Avg. CPE": 0.0, "Avg. Cost": 0.05, "Campaign ID": 819467226, "Avg. CPC": 0.05, "Interaction Types": ["Clicks"], "Account Name": "[W] G1 - WPL - vltkw360", "Engagements": 0, "Date": "2017-08-09", "Advertising Channel": "Search", "Campaign state": "enabled", "Video played to 100%": 0.0, "Avg. CPM": 30.0, "Bid Strategy Type": "cpc", "Clicks": 3, "Cost": 0.15, "Campaign serving status": "eligible", "Invalid clicks": 0, "Impressions": 5, "Video played to 50%": 0.0, "End date": "", "Video played to 75%": 0.0, "View rate": 0.0, "Unique cookies": "", "Views": 0, "Account ID": "5993679244", "Campaign": "Brand-term_EX_down-vo-lam"}, {"Advertising Sub Channel": "", "Avg. position": 1.0, "Mapping": false, "Conversions": 0.0, "Avg. CPV": 0.0, "CTR": 20.0, "Video played to 25%": 0.0, "Start date": "2017-05-04", "Interactions": 1, "Interaction Rate": 20.0, "Avg. CPE": 0.0, "Avg. Cost": 0.02, "Campaign ID": 819467232, "Avg. CPC": 0.02, "Interaction Types": ["Clicks"], "Account Name": "[W] G1 - WPL - vltkw360", "Engagements": 0, "Date": "2017-08-09", "Advertising Channel": "Search", "Campaign state": "enabled", "Video played to 100%": 0.0, "Avg. CPM": 4.0, "Bid Strategy Type": "cpc", "Clicks": 1, "Cost": 0.02, "Campaign serving status": "eligible", "Invalid clicks": 0, "Impressions": 5, "Video played to 50%": 0.0, "End date": "", "Video played to 75%": 0.0, "View rate": 0.0, "Unique cookies": "", "Views": 0, "Account ID": "5993679244", "Campaign": "Brand-term_EX_game-vo-lam"}, {"Advertising Sub Channel": "", "Avg. position": 1.3, "Mapping": false, "Conversions": 17.0, "Avg. CPV": 0.0, "CTR": 28.74, "Video played to 25%": 0.0, "Start date": "2017-05-04", "Interactions": 192, "Interaction Rate": 28.74, "Avg. CPE": 0.0, "Avg. Cost": 0.02875, "Campaign ID": 819466977, "Avg. CPC": 0.02875, "Interaction Types": ["Clicks"], "Account Name": "[W] G1 - WPL - vltkw360", "Engagements": 0, "Date": "2017-08-09", "Advertising Channel": "Search", "Campaign state": "enabled", "Video played to 100%": 0.0, "Avg. CPM": 8.263473, "Bid Strategy Type": "cpc", "Clicks": 192, "Cost": 5.52, "Campaign serving status": "eligible", "Invalid clicks": 12, "Impressions": 668, "Video played to 50%": 0.0, "End date": "", "Video played to 75%": 0.0, "View rate": 0.0, "Unique cookies": "", "Views": 0, "Account ID": "5993679244", "Campaign": "Brand-term_BM_vo-lam-truyen-ky"}, {"Advertising Sub Channel": "", "Avg. position": 1.3, "Mapping": false, "Conversions": 5.0, "Avg. CPV": 0.0, "CTR": 33.33, "Video played to 25%": 0.0, "Start date": "2017-05-04", "Interactions": 19, "Interaction Rate": 33.33, "Avg. CPE": 0.0, "Avg. Cost": 0.030526, "Campaign ID": 819466980, "Avg. CPC": 0.030526, "Interaction Types": ["Clicks"], "Account Name": "[W] G1 - WPL - vltkw360", "Engagements": 0, "Date": "2017-08-09", "Advertising Channel": "Search", "Campaign state": "enabled", "Video played to 100%": 0.0, "Avg. CPM": 10.175439, "Bid Strategy Type": "cpc", "Clicks": 19, "Cost": 0.58, "Campaign serving status": "eligible", "Invalid clicks": 7, "Impressions": 57, "Video played to 50%": 0.0, "End date": "", "Video played to 75%": 0.0, "View rate": 0.0, "Unique cookies": "", "Views": 0, "Account ID": "5993679244", "Campaign": "Brand-term_BM_vo-lam-other"}, {"Advertising Sub Channel": "", "Avg. position": 1.3, "Mapping": false, "Conversions": 22.0, "Avg. CPV": 0.0, "CTR": 25.27, "Video played to 25%": 0.0, "Start date": "2017-05-04", "Interactions": 188, "Interaction Rate": 25.27, "Avg. CPE": 0.0, "Avg. Cost": 0.033564, "Campaign ID": 819467001, "Avg. CPC": 0.033564, "Interaction Types": ["Clicks"], "Account Name": "[W] G1 - WPL - vltkw360", "Engagements": 0, "Date": "2017-08-09", "Advertising Channel": "Search", "Campaign state": "enabled", "Video played to 100%": 0.0, "Avg. CPM": 8.481183, "Bid Strategy Type": "cpc", "Clicks": 188, "Cost": 6.31, "Campaign serving status": "eligible", "Invalid clicks": 3, "Impressions": 744, "Video played to 50%": 0.0, "End date": "", "Video played to 75%": 0.0, "View rate": 0.0, "Unique cookies": "", "Views": 0, "Account ID": "5993679244", "Campaign": "Brand-term_BM_vltk"}, {"Advertising Sub Channel": "", "Avg. position": 1.2, "Mapping": false, "Conversions": 22.0, "Avg. CPV": 0.0, "CTR": 34.96, "Video played to 25%": 0.0, "Start date": "2017-05-04", "Interactions": 186, "Interaction Rate": 34.96, "Avg. CPE": 0.0, "Avg. Cost": 0.027742, "Campaign ID": 819467034, "Avg. CPC": 0.027742, "Interaction Types": ["Clicks"], "Account Name": "[W] G1 - WPL - vltkw360", "Engagements": 0, "Date": "2017-08-09", "Advertising Channel": "Search", "Campaign state": "enabled", "Video played to 100%": 0.0, "Avg. CPM": 9.699248, "Bid Strategy Type": "cpc", "Clicks": 186, "Cost": 5.16, "Campaign serving status": "eligible", "Invalid clicks": 14, "Impressions": 532, "Video played to 50%": 0.0, "End date": "", "Video played to 75%": 0.0, "View rate": 0.0, "Unique cookies": "", "Views": 0, "Account ID": "5993679244", "Campaign": "Brand-term_BM_zing-vo-lam-truyen-ky"}, {"Advertising Sub Channel": "", "Avg. position": 1.0, "Mapping": false, "Conversions": 0.0, "Avg. CPV": 0.0, "CTR": 100.0, "Video played to 25%": 0.0, "Start date": "2017-05-04", "Interactions": 1, "Interaction Rate": 100.0, "Avg. CPE": 0.0, "Avg. Cost": 0.24, "Campaign ID": 819467217, "Avg. CPC": 0.24, "Interaction Types": ["Clicks"], "Account Name": "[W] G1 - WPL - vltkw360", "Engagements": 0, "Date": "2017-08-09", "Advertising Channel": "Search", "Campaign state": "enabled", "Video played to 100%": 0.0, "Avg. CPM": 240.0, "Bid Strategy Type": "cpc", "Clicks": 1, "Cost": 0.24, "Campaign serving status": "eligible", "Invalid clicks": 0, "Impressions": 1, "Video played to 50%": 0.0, "End date": "", "Video played to 75%": 0.0, "View rate": 0.0, "Unique cookies": "", "Views": 0, "Account ID": "5993679244", "Campaign": "Brand-term_EX_360-vo-lam-truyen-ky"}, {"Advertising Sub Channel": "", "Avg. position": 1.1, "Mapping": false, "Conversions": 85.0, "Avg. CPV": 0.0, "CTR": 47.37, "Video played to 25%": 0.0, "Start date": "2017-05-04", "Interactions": 1037, "Interaction Rate": 47.37, "Avg. CPE": 0.0, "Avg. Cost": 0.019219, "Campaign ID": 819466989, "Avg. CPC": 0.019219, "Interaction Types": ["Clicks"], "Account Name": "[W] G1 - WPL - vltkw360", "Engagements": 0, "Date": "2017-08-09", "Advertising Channel": "Search", "Campaign state": "enabled", "Video played to 100%": 0.0, "Avg. CPM": 9.104614, "Bid Strategy Type": "cpc", "Clicks": 1037, "Cost": 19.93, "Campaign serving status": "eligible", "Invalid clicks": 58, "Impressions": 2189, "Video played to 50%": 0.0, "End date": "", "Video played to 75%": 0.0, "View rate": 0.0, "Unique cookies": "", "Views": 0, "Account ID": "5993679244", "Campaign": "Brand-term_BM_game-vo-lam"}, {"Advertising Sub Channel": "", "Avg. position": 1.2, "Mapping": false, "Conversions": 1.0, "Avg. CPV": 0.0, "CTR": 31.91, "Video played to 25%": 0.0, "Start date": "2017-05-04", "Interactions": 15, "Interaction Rate": 31.91, "Avg. CPE": 0.0, "Avg. Cost": 0.024, "Campaign ID": 819466992, "Avg. CPC": 0.024, "Interaction Types": ["Clicks"], "Account Name": "[W] G1 - WPL - vltkw360", "Engagements": 0, "Date": "2017-08-09", "Advertising Channel": "Search", "Campaign state": "enabled", "Video played to 100%": 0.0, "Avg. CPM": 7.659574, "Bid Strategy Type": "cpc", "Clicks": 15, "Cost": 0.36, "Campaign serving status": "eligible", "Invalid clicks": 1, "Impressions": 47, "Video played to 50%": 0.0, "End date": "", "Video played to 75%": 0.0, "View rate": 0.0, "Unique cookies": "", "Views": 0, "Account ID": "5993679244", "Campaign": "Brand-term_BM_game-vltk"}, {"Advertising Sub Channel": "", "Avg. position": 1.2, "Mapping": false, "Conversions": 40.0, "Avg. CPV": 0.0, "CTR": 49.57, "Video played to 25%": 0.0, "Start date": "2017-05-04", "Interactions": 289, "Interaction Rate": 49.57, "Avg. CPE": 0.0, "Avg. Cost": 0.020692, "Campaign ID": 819467007, "Avg. CPC": 0.020692, "Interaction Types": ["Clicks"], "Account Name": "[W] G1 - WPL - vltkw360", "Engagements": 0, "Date": "2017-08-09", "Advertising Channel": "Search", "Campaign state": "enabled", "Video played to 100%": 0.0, "Avg. CPM": 10.25729, "Bid Strategy Type": "cpc", "Clicks": 289, "Cost": 5.98, "Campaign serving status": "eligible", "Invalid clicks": 13, "Impressions": 583, "Video played to 50%": 0.0, "End date": "", "Video played to 75%": 0.0, "View rate": 0.0, "Unique cookies": "", "Views": 0, "Account ID": "5993679244", "Campaign": "Brand-term_BM_web-vo-lam-truyen-ky"}, {"Advertising Sub Channel": "", "Avg. position": 1.4, "Mapping": false, "Conversions": 0.0, "Avg. CPV": 0.0, "CTR": 19.23, "Video played to 25%": 0.0, "Start date": "2017-05-04", "Interactions": 5, "Interaction Rate": 19.23, "Avg. CPE": 0.0, "Avg. Cost": 0.044, "Campaign ID": 819466986, "Avg. CPC": 0.044, "Interaction Types": ["Clicks"], "Account Name": "[W] G1 - WPL - vltkw360", "Engagements": 0, "Date": "2017-08-09", "Advertising Channel": "Search", "Campaign state": "enabled", "Video played to 100%": 0.0, "Avg. CPM": 8.461538, "Bid Strategy Type": "cpc", "Clicks": 5, "Cost": 0.22, "Campaign serving status": "eligible", "Invalid clicks": 0, "Impressions": 26, "Video played to 50%": 0.0, "End date": "", "Video played to 75%": 0.0, "View rate": 0.0, "Unique cookies": "", "Views": 0, "Account ID": "5993679244", "Campaign": "Brand-term_BM_down-vo-lam"}, {"Advertising Sub Channel": "", "Avg. position": 1.2, "Mapping": false, "Conversions": 22.0, "Avg. CPV": 0.0, "CTR": 36.88, "Video played to 25%": 0.0, "Start date": "2017-05-04", "Interactions": 118, "Interaction Rate": 36.88, "Avg. CPE": 0.0, "Avg. Cost": 0.025254, "Campaign ID": 819467016, "Avg. CPC": 0.025254, "Interaction Types": ["Clicks"], "Account Name": "[W] G1 - WPL - vltkw360", "Engagements": 0, "Date": "2017-08-09", "Advertising Channel": "Search", "Campaign state": "enabled", "Video played to 100%": 0.0, "Avg. CPM": 9.3125, "Bid Strategy Type": "cpc", "Clicks": 118, "Cost": 2.98, "Campaign serving status": "eligible", "Invalid clicks": 21, "Impressions": 320, "Video played to 50%": 0.0, "End date": "", "Video played to 75%": 0.0, "View rate": 0.0, "Unique cookies": "", "Views": 0, "Account ID": "5993679244", "Campaign": "Brand-term_BM_web-vltk"}, {"Advertising Sub Channel": "", "Avg. position": 1.8, "Mapping": false, "Conversions": 1.0, "Avg. CPV": 0.0, "CTR": 16.67, "Video played to 25%": 0.0, "Start date": "2017-05-04", "Interactions": 1, "Interaction Rate": 16.67, "Avg. CPE": 0.0, "Avg. Cost": 0.01, "Campaign ID": 819467028, "Avg. CPC": 0.01, "Interaction Types": ["Clicks"], "Account Name": "[W] G1 - WPL - vltkw360", "Engagements": 0, "Date": "2017-08-09", "Advertising Channel": "Search", "Campaign state": "enabled", "Video played to 100%": 0.0, "Avg. CPM": 1.666667, "Bid Strategy Type": "cpc", "Clicks": 1, "Cost": 0.01, "Campaign serving status": "eligible", "Invalid clicks": 0, "Impressions": 6, "Video played to 50%": 0.0, "End date": "", "Video played to 75%": 0.0, "View rate": 0.0, "Unique cookies": "", "Views": 0, "Account ID": "5993679244", "Campaign": "Brand-term_BM_360-game-vo-lam-truyen-ky"}, {"Advertising Sub Channel": "", "Avg. position": 1.5, "Mapping": false, "Conversions": 3.0, "Avg. CPV": 0.0, "CTR": 27.16, "Video played to 25%": 0.0, "Start date": "2017-05-04", "Interactions": 22, "Interaction Rate": 27.16, "Avg. CPE": 0.0, "Avg. Cost": 0.05, "Campaign ID": 819467184, "Avg. CPC": 0.05, "Interaction Types": ["Clicks"], "Account Name": "[W] G1 - WPL - vltkw360", "Engagements": 0, "Date": "2017-08-09", "Advertising Channel": "Search", "Campaign state": "enabled", "Video played to 100%": 0.0, "Avg. CPM": 13.580247, "Bid Strategy Type": "cpc", "Clicks": 22, "Cost": 1.1, "Campaign serving status": "eligible", "Invalid clicks": 0, "Impressions": 81, "Video played to 50%": 0.0, "End date": "", "Video played to 75%": 0.0, "View rate": 0.0, "Unique cookies": "", "Views": 0, "Account ID": "5993679244", "Campaign": "Brand-term_PM_vo-lam"}, {"Advertising Sub Channel": "", "Avg. position": 1.4, "Mapping": false, "Conversions": 0.0, "Avg. CPV": 0.0, "CTR": 22.22, "Video played to 25%": 0.0, "Start date": "2017-05-04", "Interactions": 2, "Interaction Rate": 22.22, "Avg. CPE": 0.0, "Avg. Cost": 0.04, "Campaign ID": 819467241, "Avg. CPC": 0.04, "Interaction Types": ["Clicks"], "Account Name": "[W] G1 - WPL - vltkw360", "Engagements": 0, "Date": "2017-08-09", "Advertising Channel": "Search", "Campaign state": "enabled", "Video played to 100%": 0.0, "Avg. CPM": 8.888889, "Bid Strategy Type": "cpc", "Clicks": 2, "Cost": 0.08, "Campaign serving status": "eligible", "Invalid clicks": 0, "Impressions": 9, "Video played to 50%": 0.0, "End date": "", "Video played to 75%": 0.0, "View rate": 0.0, "Unique cookies": "", "Views": 0, "Account ID": "5993679244", "Campaign": "Brand-term_EX_vo-lam"}, {"Advertising Sub Channel": "", "Avg. position": 1.7, "Mapping": false, "Conversions": 13.0, "Avg. CPV": 0.0, "CTR": 50.11, "Video played to 25%": 0.0, "Start date": "2017-05-04", "Interactions": 227, "Interaction Rate": 50.11, "Avg. CPE": 0.0, "Avg. Cost": 0.033612, "Campaign ID": 819467247, "Avg. CPC": 0.033612, "Interaction Types": ["Clicks"], "Account Name": "[W] G1 - WPL - vltkw360", "Engagements": 0, "Date": "2017-08-09", "Advertising Channel": "Search", "Campaign state": "enabled", "Video played to 100%": 0.0, "Avg. CPM": 16.843267, "Bid Strategy Type": "cpc", "Clicks": 227, "Cost": 7.63, "Campaign serving status": "eligible", "Invalid clicks": 17, "Impressions": 453, "Video played to 50%": 0.0, "End date": "", "Video played to 75%": 0.0, "View rate": 0.0, "Unique cookies": "", "Views": 0, "Account ID": "5993679244", "Campaign": "Brand-term_EX_vo-lam-truyen-ky"}, {"Advertising Sub Channel": "", "Avg. position": 1.3, "Mapping": false, "Conversions": 0.0, "Avg. CPV": 0.0, "CTR": 75.0, "Video played to 25%": 0.0, "Start date": "2017-05-04", "Interactions": 3, "Interaction Rate": 75.0, "Avg. CPE": 0.0, "Avg. Cost": 0.06, "Campaign ID": 819467262, "Avg. CPC": 0.06, "Interaction Types": ["Clicks"], "Account Name": "[W] G1 - WPL - vltkw360", "Engagements": 0, "Date": "2017-08-09", "Advertising Channel": "Search", "Campaign state": "enabled", "Video played to 100%": 0.0, "Avg. CPM": 45.0, "Bid Strategy Type": "cpc", "Clicks": 3, "Cost": 0.18, "Campaign serving status": "eligible", "Invalid clicks": 1, "Impressions": 4, "Video played to 50%": 0.0, "End date": "", "Video played to 75%": 0.0, "View rate": 0.0, "Unique cookies": "", "Views": 0, "Account ID": "5993679244", "Campaign": "Brand-term_EX_webgame-vltk"}, {"Advertising Sub Channel": "", "Avg. position": 1.2, "Mapping": false, "Conversions": 31.0, "Avg. CPV": 0.0, "CTR": 50.82, "Video played to 25%": 0.0, "Start date": "2017-05-04", "Interactions": 155, "Interaction Rate": 50.82, "Avg. CPE": 0.0, "Avg. Cost": 0.022968, "Campaign ID": 819466983, "Avg. CPC": 0.022968, "Interaction Types": ["Clicks"], "Account Name": "[W] G1 - WPL - vltkw360", "Engagements": 0, "Date": "2017-08-09", "Advertising Channel": "Search", "Campaign state": "enabled", "Video played to 100%": 0.0, "Avg. CPM": 11.672131, "Bid Strategy Type": "cpc", "Clicks": 155, "Cost": 3.56, "Campaign serving status": "eligible", "Invalid clicks": 8, "Impressions": 305, "Video played to 50%": 0.0, "End date": "", "Video played to 75%": 0.0, "View rate": 0.0, "Unique cookies": "", "Views": 0, "Account ID": "5993679244", "Campaign": "Brand-term_BM_dang-ky-vo-lam"}, {"Advertising Sub Channel": "", "Avg. position": 1.1, "Mapping": false, "Conversions": 56.0, "Avg. CPV": 0.0, "CTR": 56.39, "Video played to 25%": 0.0, "Start date": "2017-05-04", "Interactions": 309, "Interaction Rate": 56.39, "Avg. CPE": 0.0, "Avg. Cost": 0.016731, "Campaign ID": 819467010, "Avg. CPC": 0.016731, "Interaction Types": ["Clicks"], "Account Name": "[W] G1 - WPL - vltkw360", "Engagements": 0, "Date": "2017-08-09", "Advertising Channel": "Search", "Campaign state": "enabled", "Video played to 100%": 0.0, "Avg. CPM": 9.434307, "Bid Strategy Type": "cpc", "Clicks": 309, "Cost": 5.17, "Campaign serving status": "eligible", "Invalid clicks": 27, "Impressions": 548, "Video played to 50%": 0.0, "End date": "", "Video played to 75%": 0.0, "View rate": 0.0, "Unique cookies": "", "Views": 0, "Account ID": "5993679244", "Campaign": "Brand-term_BM_web-game-vo-lam-truyen-ky"}, {"Advertising Sub Channel": "", "Avg. position": 1.2, "Mapping": false, "Conversions": 4.0, "Avg. CPV": 0.0, "CTR": 33.33, "Video played to 25%": 0.0, "Start date": "2017-05-04", "Interactions": 33, "Interaction Rate": 33.33, "Avg. CPE": 0.0, "Avg. Cost": 0.034242, "Campaign ID": 819467019, "Avg. CPC": 0.034242, "Interaction Types": ["Clicks"], "Account Name": "[W] G1 - WPL - vltkw360", "Engagements": 0, "Date": "2017-08-09", "Advertising Channel": "Search", "Campaign state": "enabled", "Video played to 100%": 0.0, "Avg. CPM": 11.414141, "Bid Strategy Type": "cpc", "Clicks": 33, "Cost": 1.13, "Campaign serving status": "eligible", "Invalid clicks": 1, "Impressions": 99, "Video played to 50%": 0.0, "End date": "", "Video played to 75%": 0.0, "View rate": 0.0, "Unique cookies": "", "Views": 0, "Account ID": "5993679244", "Campaign": "Brand-term_BM_web-game-vltk"}, {"Advertising Sub Channel": "", "Avg. position": 2.8, "Mapping": false, "Conversions": 0.0, "Avg. CPV": 0.0, "CTR": 91.67, "Video played to 25%": 0.0, "Start date": "2017-05-04", "Interactions": 11, "Interaction Rate": 91.67, "Avg. CPE": 0.0, "Avg. Cost": 0.01, "Campaign ID": 819467196, "Avg. CPC": 0.01, "Interaction Types": ["Clicks"], "Account Name": "[W] G1 - WPL - vltkw360", "Engagements": 0, "Date": "2017-08-09", "Advertising Channel": "Search", "Campaign state": "enabled", "Video played to 100%": 0.0, "Avg. CPM": 9.166667, "Bid Strategy Type": "cpc", "Clicks": 11, "Cost": 0.11, "Campaign serving status": "eligible", "Invalid clicks": 1, "Impressions": 12, "Video played to 50%": 0.0, "End date": "", "Video played to 75%": 0.0, "View rate": 0.0, "Unique cookies": "", "Views": 0, "Account ID": "5993679244", "Campaign": "Brand-term_PM_web-game-vo-lam-truyen-ky"}, {"Advertising Sub Channel": "", "Avg. position": 1.0, "Mapping": false, "Conversions": 0.0, "Avg. CPV": 0.0, "CTR": 100.0, "Video played to 25%": 0.0, "Start date": "2017-05-04", "Interactions": 1, "Interaction Rate": 100.0, "Avg. CPE": 0.0, "Avg. Cost": 0.01, "Campaign ID": 819467256, "Avg. CPC": 0.01, "Interaction Types": ["Clicks"], "Account Name": "[W] G1 - WPL - vltkw360", "Engagements": 0, "Date": "2017-08-09", "Advertising Channel": "Search", "Campaign state": "enabled", "Video played to 100%": 0.0, "Avg. CPM": 10.0, "Bid Strategy Type": "cpc", "Clicks": 1, "Cost": 0.01, "Campaign serving status": "eligible", "Invalid clicks": 0, "Impressions": 1, "Video played to 50%": 0.0, "End date": "", "Video played to 75%": 0.0, "View rate": 0.0, "Unique cookies": "", "Views": 0, "Account ID": "5993679244", "Campaign": "Brand-term_EX_web-vltk"}, {"Advertising Sub Channel": "", "Avg. position": 1.2, "Mapping": false, "Conversions": 390.0, "Avg. CPV": 0.0, "CTR": 44.11, "Video played to 25%": 0.0, "Start date": "", "Interactions": 3788, "Interaction Rate": 44.11, "Avg. CPE": 0.0, "Avg. Cost": 0.022315, "Campaign ID": "", "Avg. CPC": 0.022315, "Interaction Types": "", "Account Name": "[W] G1 - WPL - vltkw360", "Engagements": 0, "Date": "2017-08-09", "Advertising Channel": "", "Campaign state": "Total", "Video played to 100%": 0.0, "Avg. CPM": 9.842804, "Bid Strategy Type": "", "Clicks": 3788, "Cost": 84.53, "Campaign serving status": "", "Invalid clicks": 240, "Impressions": 8588, "Video played to 50%": 0.0, "End date": "", "Video played to 75%": 0.0, "View rate": 0.0, "Unique cookies": "", "Views": 0, "Account ID": "5993679244", "Campaign": ""}]