[{"Advertising Sub Channel": "", "Avg. position": 1.4, "Mapping": false, "Conversions": 23.0, "Avg. CPV": 0.0, "CTR": 20.25, "Video played to 25%": 0.0, "Start date": "2014-07-09", "Interactions": 81, "Interaction Rate": 20.25, "Avg. CPE": 0.0, "Avg. Cost": 0.028519, "Campaign ID": 192460947, "Avg. CPC": 0.028519, "Interaction Types": ["Clicks"], "Account Name": "[W] G1 - WPL - phongvan360", "Engagements": 0, "Date": "2017-08-01", "Advertising Channel": "Search", "Campaign state": "paused", "Video played to 100%": 0.0, "Avg. CPM": 5.775, "Bid Strategy Type": "cpc", "Clicks": 81, "Cost": 2.31, "Campaign serving status": "eligible", "Invalid clicks": 9, "Impressions": 400, "Video played to 50%": 0.0, "End date": "", "Video played to 75%": 0.0, "View rate": 0.0, "Unique cookies": "", "Views": 0, "Account ID": "1493302671", "Campaign": "Brand-term_Game PhongVan"}, {"Advertising Sub Channel": "", "Avg. position": 1.0, "Mapping": false, "Conversions": 37.0, "Avg. CPV": 0.0, "CTR": 25.57, "Video played to 25%": 0.0, "Start date": "2014-07-09", "Interactions": 179, "Interaction Rate": 25.57, "Avg. CPE": 0.0, "Avg. Cost": 0.052682, "Campaign ID": 192461067, "Avg. CPC": 0.052682, "Interaction Types": ["Clicks"], "Account Name": "[W] G1 - WPL - phongvan360", "Engagements": 0, "Date": "2017-08-01", "Advertising Channel": "Search", "Campaign state": "paused", "Video played to 100%": 0.0, "Avg. CPM": 13.471429, "Bid Strategy Type": "cpc", "Clicks": 179, "Cost": 9.43, "Campaign serving status": "eligible", "Invalid clicks": 8, "Impressions": 700, "Video played to 50%": 0.0, "End date": "", "Video played to 75%": 0.0, "View rate": 0.0, "Unique cookies": "", "Views": 0, "Account ID": "1493302671", "Campaign": "Brand-term_PhongVan"}, {"Advertising Sub Channel": "", "Avg. position": 1.6, "Mapping": false, "Conversions": 1.0, "Avg. CPV": 0.0, "CTR": 14.29, "Video played to 25%": 0.0, "Start date": "2015-09-01", "Interactions": 3, "Interaction Rate": 14.29, "Avg. CPE": 0.0, "Avg. Cost": 0.04, "Campaign ID": 280122747, "Avg. CPC": 0.04, "Interaction Types": ["Clicks"], "Account Name": "[W] G1 - WPL - phongvan360", "Engagements": 0, "Date": "2017-08-01", "Advertising Channel": "Search", "Campaign state": "paused", "Video played to 100%": 0.0, "Avg. CPM": 5.714286, "Bid Strategy Type": "cpc", "Clicks": 3, "Cost": 0.12, "Campaign serving status": "eligible", "Invalid clicks": 0, "Impressions": 21, "Video played to 50%": 0.0, "End date": "", "Video played to 75%": 0.0, "View rate": 0.0, "Unique cookies": "", "Views": 0, "Account ID": "1493302671", "Campaign": "Competitor-term_Tan PhongVan"}, {"Advertising Sub Channel": "", "Avg. position": 1.2, "Mapping": false, "Conversions": 61.0, "Avg. CPV": 0.0, "CTR": 23.46, "Video played to 25%": 0.0, "Start date": "", "Interactions": 263, "Interaction Rate": 23.46, "Avg. CPE": 0.0, "Avg. Cost": 0.045095, "Campaign ID": "", "Avg. CPC": 0.045095, "Interaction Types": "", "Account Name": "[W] G1 - WPL - phongvan360", "Engagements": 0, "Date": "2017-08-01", "Advertising Channel": "", "Campaign state": "Total", "Video played to 100%": 0.0, "Avg. CPM": 10.579839, "Bid Strategy Type": "", "Clicks": 263, "Cost": 11.86, "Campaign serving status": "", "Invalid clicks": 17, "Impressions": 1121, "Video played to 50%": 0.0, "End date": "", "Video played to 75%": 0.0, "View rate": 0.0, "Unique cookies": "", "Views": 0, "Account ID": "1493302671", "Campaign": ""}]