[{"Avg. position": 1.0, "Views": 0, "Start date": "2017-05-26", "Campaign serving status": "eligible", "Avg. Cost": 0.017916, "Interaction Rate": 1.46, "Interaction Types": ["Clicks"], "View rate": 0.0, "Campaign state": "paused", "Campaign": "JXM | 1705015 1706010 1707028 | Branding GDN - iOS", "Video played to 25%": 0.0, "Conversions": 21.0, "Invalid clicks": 306, "Cost": 70.41, "Unique cookies": 114872, "Impressions": 269932, "Avg. CPC": 0.017916, "Advertising Channel": "Display", "Advertising Sub Channel": "", "Campaign ID": 837910039, "End date": "", "Mapping": false, "Account Name": "VNG - PG1 - JXM", "Engagements": 0, "Bid Strategy Type": "Maximize clicks", "Clicks": 3930, "CTR": 1.46, "Video played to 100%": 0.0, "Avg. CPE": 0.0, "Video played to 75%": 0.0, "Avg. CPM": 0.260843, "Date": "2017-07-06", "Avg. CPV": 0.0, "Account ID": "5008396449", "Interactions": 3930, "Video played to 50%": 0.0}, {"Avg. position": 1.0, "Views": 0, "Start date": "2016-10-16", "Campaign serving status": "eligible", "Avg. Cost": 0.017334, "Interaction Rate": 65.99, "Interaction Types": ["Clicks"], "View rate": 0.0, "Campaign state": "enabled", "Campaign": "JXM | 1610105 1611013 1611026 1611062 1703048 1704017 1705015 1706010 1707028 1709054 | Search Desktop Only", "Video played to 25%": 0.0, "Conversions": 0.0, "Invalid clicks": 85, "Cost": 23.54, "Unique cookies": "", "Impressions": 2058, "Avg. CPC": 0.017334, "Advertising Channel": "Search", "Advertising Sub Channel": "", "Campaign ID": 682542681, "End date": "", "Mapping": false, "Account Name": "VNG - PG1 - JXM", "Engagements": 0, "Bid Strategy Type": "Maximize clicks", "Clicks": 1358, "CTR": 65.99, "Video played to 100%": 0.0, "Avg. CPE": 0.0, "Video played to 75%": 0.0, "Avg. CPM": 11.43829, "Date": "2017-07-06", "Avg. CPV": 0.0, "Account ID": "5008396449", "Interactions": 1358, "Video played to 50%": 0.0}, {"Avg. position": 1.3, "Views": 0, "Start date": "2016-10-16", "Campaign serving status": "eligible", "Avg. Cost": 0.143925, "Interaction Rate": 15.76, "Interaction Types": ["Clicks"], "View rate": 0.0, "Campaign state": "enabled", "Campaign": "JXM | 1610105 1611013 1611026 1611062 1703048 1704016 1706008 1707026 1709039 | Search Google Play Store", "Video played to 25%": 0.0, "Conversions": 959.0, "Invalid clicks": 846, "Cost": 407.02, "Unique cookies": "", "Impressions": 17942, "Avg. CPC": 0.143925, "Advertising Channel": "Search", "Advertising Sub Channel": "Search Mobile App", "Campaign ID": 682545537, "End date": "", "Mapping": false, "Account Name": "VNG - PG1 - JXM", "Engagements": 0, "Bid Strategy Type": "Target CPA", "Clicks": 2828, "CTR": 15.76, "Video played to 100%": 0.0, "Avg. CPE": 0.0, "Video played to 75%": 0.0, "Avg. CPM": 22.685319, "Date": "2017-07-06", "Avg. CPV": 0.0, "Account ID": "5008396449", "Interactions": 2828, "Video played to 50%": 0.0}, {"Avg. position": 1.0, "Views": 0, "Start date": "2017-06-02", "Campaign serving status": "eligible", "Avg. Cost": 0.016597, "Interaction Rate": 1.4, "Interaction Types": ["Clicks"], "View rate": 0.0, "Campaign state": "paused", "Campaign": "JXM | 1705015 1706010 1707028 | Branding GDN - Android", "Video played to 25%": 0.0, "Conversions": 35.0, "Invalid clicks": 1405, "Cost": 110.5, "Unique cookies": 214297, "Impressions": 475143, "Avg. CPC": 0.016597, "Advertising Channel": "Display", "Advertising Sub Channel": "", "Campaign ID": 843945598, "End date": "", "Mapping": false, "Account Name": "VNG - PG1 - JXM", "Engagements": 0, "Bid Strategy Type": "Maximize clicks", "Clicks": 6658, "CTR": 1.4, "Video played to 100%": 0.0, "Avg. CPE": 0.0, "Video played to 75%": 0.0, "Avg. CPM": 0.232562, "Date": "2017-07-06", "Avg. CPV": 0.0, "Account ID": "5008396449", "Interactions": 6658, "Video played to 50%": 0.0}, {"Avg. position": 1.3, "Views": 15776, "Start date": "2016-11-15", "Campaign serving status": "eligible", "Avg. Cost": 0.013961, "Interaction Rate": 7.09, "Interaction Types": ["Clicks", "Engagements", "Views"], "View rate": 15.45, "Campaign state": "enabled", "Campaign": "JXM | 1610105 1611013 1611026 1611062 1703048 1706008 1707026 1709039 | UAC GMG Android", "Video played to 25%": 24.92, "Conversions": 910.0, "Invalid clicks": 622, "Cost": 406.62161, "Unique cookies": "", "Impressions": 410534, "Avg. CPC": 0.078091, "Advertising Channel": "Multi Channel", "Advertising Sub Channel": "Universal App Campaign", "Campaign ID": 699351990, "End date": "", "Mapping": false, "Account Name": "VNG - PG1 - JXM", "Engagements": 16194, "Bid Strategy Type": "Target CPA", "Clicks": 5207, "CTR": 1.27, "Video played to 100%": 9.75, "Avg. CPE": 0.012556, "Video played to 75%": 11.85, "Avg. CPM": 0.99047, "Date": "2017-07-06", "Avg. CPV": 0.012882, "Account ID": "5008396449", "Interactions": 29126, "Video played to 50%": 15.22}, {"Avg. position": 1.0, "Views": 11031, "Start date": "2016-12-28", "Campaign serving status": "eligible", "Avg. Cost": 0.025401, "Interaction Rate": 2.76, "Interaction Types": ["Clicks", "Engagements", "Views"], "View rate": 16.39, "Campaign state": "enabled", "Campaign": "JXM | 1610105 1611013 1611026 1611062 1703048 1704016 1706008 1707026 1709039 | UAC App Store - iOS", "Video played to 25%": 21.57, "Conversions": 451.0, "Invalid clicks": 477, "Cost": 509.12075, "Unique cookies": "", "Impressions": 727198, "Avg. CPC": 0.07583, "Advertising Channel": "Multi Channel", "Advertising Sub Channel": "Universal App Campaign", "Campaign ID": 726209660, "End date": "", "Mapping": false, "Account Name": "VNG - PG1 - JXM", "Engagements": 4699, "Bid Strategy Type": "Target CPA", "Clicks": 6714, "CTR": 0.92, "Video played to 100%": 5.94, "Avg. CPE": 0.032358, "Video played to 75%": 7.77, "Avg. CPM": 0.700113, "Date": "2017-07-06", "Avg. CPV": 0.013766, "Account ID": "5008396449", "Interactions": 20043, "Video played to 50%": 10.26}, {"Avg. position": 1.1, "Views": 26807, "Start date": "", "Campaign serving status": "", "Avg. Cost": 0.023884, "Interaction Rate": 3.36, "Interaction Types": "", "View rate": 15.83, "Campaign state": "Total", "Campaign": "", "Video played to 25%": 22.71, "Conversions": 2376.0, "Invalid clicks": 3741, "Cost": 1527.21236, "Unique cookies": "", "Impressions": 1902807, "Avg. CPC": 0.05721, "Advertising Channel": "", "Advertising Sub Channel": "", "Campaign ID": "", "End date": "", "Mapping": false, "Account Name": "VNG - PG1 - JXM", "Engagements": 20893, "Bid Strategy Type": "", "Clicks": 26695, "CTR": 1.4, "Video played to 100%": 7.24, "Avg. CPE": 0.01701, "Video played to 75%": 9.17, "Avg. CPM": 0.80261, "Date": "2017-07-06", "Avg. CPV": 0.013246, "Account ID": "5008396449", "Interactions": 63943, "Video played to 50%": 11.96}]