[{"Conversions": 18.0, "Advertising Sub Channel": "", "Interaction Rate": 1.7, "Video played to 75%": 0.0, "Avg. CPE": 0.0, "Advertising Channel": "Display", "Interactions": 6282, "Invalid clicks": 628, "Unique cookies": 158209, "Date": "2017-06-23", "Account Name": "VNG - PG1 - JXM", "Video played to 100%": 0.0, "Campaign": "JXM | 1705015 1706010 1707028 | Branding GDN - iOS", "Campaign state": "paused", "Mapping": false, "Account ID": "5008396449", "Avg. CPM": 0.295082, "Views": 0, "View rate": 0.0, "CTR": 1.7, "Video played to 50%": 0.0, "End date": "", "Engagements": 0, "Campaign serving status": "eligible", "Interaction Types": ["Clicks"], "Avg. CPC": 0.017329, "Video played to 25%": 0.0, "Bid Strategy Type": "Maximize clicks", "Avg. CPV": 0.0, "Cost": 108.86, "Clicks": 6282, "Impressions": 368914, "Avg. position": 1.0, "Campaign ID": 837910039, "Start date": "2017-05-26", "Avg. Cost": 0.017329}, {"Conversions": 825.0, "Advertising Sub Channel": "Universal App Campaign", "Interaction Rate": 5.67, "Video played to 75%": 11.95, "Avg. CPE": 0.010919, "Advertising Channel": "Multi Channel", "Interactions": 12489, "Invalid clicks": 466, "Unique cookies": "", "Date": "2017-06-23", "Account Name": "VNG - PG1 - JXM", "Video played to 100%": 10.0, "Campaign": "JXM | 1610105 1611013 1611026 1611062 1703048 1706008 1707026 1709039 | UAC GMG Android", "Campaign state": "enabled", "Mapping": false, "Account ID": "5008396449", "Avg. CPM": 0.848832, "Views": 6287, "View rate": 15.13, "CTR": 1.39, "Video played to 50%": 14.78, "End date": "", "Engagements": 7137, "Campaign serving status": "eligible", "Interaction Types": ["Clicks", "Engagements", "Views"], "Avg. CPC": 0.061024, "Video played to 25%": 23.24, "Bid Strategy Type": "Target CPA", "Avg. CPV": 0.012394, "Cost": 187.09878, "Clicks": 3066, "Impressions": 220419, "Avg. position": 1.0, "Campaign ID": 699351990, "Start date": "2016-11-15", "Avg. Cost": 0.014981}, {"Conversions": 371.0, "Advertising Sub Channel": "Universal App Campaign", "Interaction Rate": 7.59, "Video played to 75%": 8.69, "Avg. CPE": 0.027198, "Advertising Channel": "Multi Channel", "Interactions": 32525, "Invalid clicks": 204, "Unique cookies": "", "Date": "2017-06-23", "Account Name": "VNG - PG1 - JXM", "Video played to 100%": 6.51, "Campaign": "JXM | 1610105 1611013 1611026 1611062 1703048 1704016 1706008 1707026 1709039 | UAC App Store - iOS", "Campaign state": "enabled", "Mapping": false, "Account ID": "5008396449", "Avg. CPM": 1.070704, "Views": 23813, "View rate": 15.68, "CTR": 0.74, "Video played to 50%": 11.18, "End date": "", "Engagements": 11646, "Campaign serving status": "eligible", "Interaction Types": ["Clicks", "Engagements", "Views"], "Avg. CPC": 0.143985, "Video played to 25%": 20.36, "Bid Strategy Type": "Target CPA", "Avg. CPV": 0.0133, "Cost": 458.73548, "Clicks": 3186, "Impressions": 428443, "Avg. position": 1.0, "Campaign ID": 726209660, "Start date": "2016-12-28", "Avg. Cost": 0.014104}, {"Conversions": 48.0, "Advertising Sub Channel": "", "Interaction Rate": 1.22, "Video played to 75%": 0.0, "Avg. CPE": 0.0, "Advertising Channel": "Display", "Interactions": 8339, "Invalid clicks": 1712, "Unique cookies": 329939, "Date": "2017-06-23", "Account Name": "VNG - PG1 - JXM", "Video played to 100%": 0.0, "Campaign": "JXM | 1705015 1706010 1707028 | Branding GDN - Android", "Campaign state": "paused", "Mapping": false, "Account ID": "5008396449", "Avg. CPM": 0.256765, "Views": 0, "View rate": 0.0, "CTR": 1.22, "Video played to 50%": 0.0, "End date": "", "Engagements": 0, "Campaign serving status": "eligible", "Interaction Types": ["Clicks"], "Avg. CPC": 0.021067, "Video played to 25%": 0.0, "Bid Strategy Type": "Maximize clicks", "Avg. CPV": 0.0, "Cost": 175.68, "Clicks": 8339, "Impressions": 684205, "Avg. position": 1.0, "Campaign ID": 843945598, "Start date": "2017-06-02", "Avg. Cost": 0.021067}, {"Conversions": 0.0, "Advertising Sub Channel": "", "Interaction Rate": 72.98, "Video played to 75%": 0.0, "Avg. CPE": 0.0, "Advertising Channel": "Search", "Interactions": 1488, "Invalid clicks": 56, "Unique cookies": "", "Date": "2017-06-23", "Account Name": "VNG - PG1 - JXM", "Video played to 100%": 0.0, "Campaign": "JXM | 1610105 1611013 1611026 1611062 1703048 1704017 1705015 1706010 1707028 1709054 | Search Desktop Only", "Campaign state": "enabled", "Mapping": false, "Account ID": "5008396449", "Avg. CPM": 11.721432, "Views": 0, "View rate": 0.0, "CTR": 72.98, "Video played to 50%": 0.0, "End date": "", "Engagements": 0, "Campaign serving status": "eligible", "Interaction Types": ["Clicks"], "Avg. CPC": 0.016062, "Video played to 25%": 0.0, "Bid Strategy Type": "Maximize clicks", "Avg. CPV": 0.0, "Cost": 23.9, "Clicks": 1488, "Impressions": 2039, "Avg. position": 1.0, "Campaign ID": 682542681, "Start date": "2016-10-16", "Avg. Cost": 0.016062}, {"Conversions": 890.0, "Advertising Sub Channel": "Search Mobile App", "Interaction Rate": 14.8, "Video played to 75%": 0.0, "Avg. CPE": 0.0, "Advertising Channel": "Search", "Interactions": 2584, "Invalid clicks": 341, "Unique cookies": "", "Date": "2017-06-23", "Account Name": "VNG - PG1 - JXM", "Video played to 100%": 0.0, "Campaign": "JXM | 1610105 1611013 1611026 1611062 1703048 1704016 1706008 1707026 1709039 | Search Google Play Store", "Campaign state": "enabled", "Mapping": false, "Account ID": "5008396449", "Avg. CPM": 22.097125, "Views": 0, "View rate": 0.0, "CTR": 14.8, "Video played to 50%": 0.0, "End date": "", "Engagements": 0, "Campaign serving status": "eligible", "Interaction Types": ["Clicks"], "Avg. CPC": 0.149327, "Video played to 25%": 0.0, "Bid Strategy Type": "Target CPA", "Avg. CPV": 0.0, "Cost": 385.86, "Clicks": 2584, "Impressions": 17462, "Avg. position": 1.3, "Campaign ID": 682545537, "Start date": "2016-10-16", "Avg. Cost": 0.149327}, {"Conversions": 2152.0, "Advertising Sub Channel": "", "Interaction Rate": 3.7, "Video played to 75%": 9.26, "Avg. CPE": 0.021012, "Advertising Channel": "", "Interactions": 63707, "Invalid clicks": 3407, "Unique cookies": "", "Date": "2017-06-23", "Account Name": "VNG - PG1 - JXM", "Video played to 100%": 7.12, "Campaign": "", "Campaign state": "Total", "Mapping": false, "Account ID": "5008396449", "Avg. CPM": 0.778477, "Views": 30100, "View rate": 15.56, "CTR": 1.45, "Video played to 50%": 11.81, "End date": "", "Engagements": 18783, "Campaign serving status": "", "Interaction Types": "", "Avg. CPC": 0.053724, "Video played to 25%": 20.86, "Bid Strategy Type": "", "Avg. CPV": 0.013111, "Cost": 1340.13426, "Clicks": 24945, "Impressions": 1721482, "Avg. position": 1.0, "Campaign ID": "", "Start date": "", "Avg. Cost": 0.021036}]