[{"Avg. CPE": 0.0, "Account Name": "VNG - PG1 - JXM", "Start date": "2017-05-26", "Engagements": 0, "Interaction Types": ["Clicks"], "Advertising Channel": "Display", "Avg. Cost": 0.017945, "Video played to 75%": 0.0, "Date": "2017-07-16", "Avg. CPM": 0.288461, "Video played to 25%": 0.0, "Bid Strategy Type": "Maximize clicks", "Unique cookies": 129555, "Account ID": "5008396449", "Invalid clicks": 369, "Campaign ID": 837910039, "Mapping": false, "Video played to 100%": 0.0, "Campaign": "JXM | 1705015 1706010 1707028 | Branding GDN - iOS", "Cost": 91.07, "Clicks": 5075, "Advertising Sub Channel": "", "Video played to 50%": 0.0, "Avg. CPV": 0.0, "View rate": 0.0, "Interactions": 5075, "Conversions": 14.0, "Campaign serving status": "eligible", "Avg. position": 1.0, "Interaction Rate": 1.61, "Campaign state": "paused", "Views": 0, "CTR": 1.61, "Avg. CPC": 0.017945, "Impressions": 315710, "End date": ""}, {"Avg. CPE": 0.009904, "Account Name": "VNG - PG1 - JXM", "Start date": "2016-11-15", "Engagements": 26606, "Interaction Types": ["Clicks", "Engagements", "Views"], "Advertising Channel": "Multi Channel", "Avg. Cost": 0.010296, "Video played to 75%": 10.91, "Date": "2017-07-16", "Avg. CPM": 1.05862, "Video played to 25%": 25.51, "Bid Strategy Type": "Target CPA", "Unique cookies": "", "Account ID": "5008396449", "Invalid clicks": 500, "Campaign ID": 699351990, "Mapping": false, "Video played to 100%": 8.35, "Campaign": "JXM | 1610105 1611013 1611026 1611062 1703048 1706008 1707026 1709039 | UAC GMG Android", "Cost": 385.27327, "Clicks": 4754, "Advertising Sub Channel": "Universal App Campaign", "Video played to 50%": 14.37, "Avg. CPV": 0.013988, "View rate": 14.73, "Interactions": 37419, "Conversions": 1202.0, "Campaign serving status": "eligible", "Avg. position": 1.1, "Interaction Rate": 10.28, "Campaign state": "enabled", "Views": 18834, "CTR": 1.31, "Avg. CPC": 0.081042, "Impressions": 363939, "End date": ""}, {"Avg. CPE": 0.014508, "Account Name": "VNG - PG1 - JXM", "Start date": "2016-12-28", "Engagements": 1624, "Interaction Types": ["Clicks", "Engagements", "Views"], "Advertising Channel": "Multi Channel", "Avg. Cost": 0.039489, "Video played to 75%": 10.66, "Date": "2017-07-16", "Avg. CPM": 0.678663, "Video played to 25%": 26.55, "Bid Strategy Type": "Target CPA", "Unique cookies": "", "Account ID": "5008396449", "Invalid clicks": 483, "Campaign ID": 726209660, "Mapping": false, "Video played to 100%": 8.78, "Campaign": "JXM | 1610105 1611013 1611026 1611062 1703048 1704016 1706008 1707026 1709039 | UAC App Store - iOS", "Cost": 356.90156, "Clicks": 6278, "Advertising Sub Channel": "Universal App Campaign", "Video played to 50%": 13.62, "Avg. CPV": 0.011323, "View rate": 18.77, "Interactions": 9038, "Conversions": 268.0, "Campaign serving status": "eligible", "Avg. position": 1.0, "Interaction Rate": 1.72, "Campaign state": "enabled", "Views": 2050, "CTR": 1.19, "Avg. CPC": 0.05685, "Impressions": 525889, "End date": ""}, {"Avg. CPE": 0.0, "Account Name": "VNG - PG1 - JXM", "Start date": "2016-10-16", "Engagements": 0, "Interaction Types": ["Clicks"], "Advertising Channel": "Search", "Avg. Cost": 0.017367, "Video played to 75%": 0.0, "Date": "2017-07-16", "Avg. CPM": 11.974382, "Video played to 25%": 0.0, "Bid Strategy Type": "Maximize clicks", "Unique cookies": "", "Account ID": "5008396449", "Invalid clicks": 80, "Campaign ID": 682542681, "Mapping": false, "Video played to 100%": 0.0, "Campaign": "JXM | 1610105 1611013 1611026 1611062 1703048 1704017 1705015 1706010 1707028 1709054 | Search Desktop Only", "Cost": 27.11, "Clicks": 1561, "Advertising Sub Channel": "", "Video played to 50%": 0.0, "Avg. CPV": 0.0, "View rate": 0.0, "Interactions": 1561, "Conversions": 0.0, "Campaign serving status": "eligible", "Avg. position": 1.0, "Interaction Rate": 68.95, "Campaign state": "enabled", "Views": 0, "CTR": 68.95, "Avg. CPC": 0.017367, "Impressions": 2264, "End date": ""}, {"Avg. CPE": 0.0, "Account Name": "VNG - PG1 - JXM", "Start date": "2017-06-02", "Engagements": 0, "Interaction Types": ["Clicks"], "Advertising Channel": "Display", "Avg. Cost": 0.016262, "Video played to 75%": 0.0, "Date": "2017-07-16", "Avg. CPM": 0.233929, "Video played to 25%": 0.0, "Bid Strategy Type": "Maximize clicks", "Unique cookies": 201728, "Account ID": "5008396449", "Invalid clicks": 1342, "Campaign ID": 843945598, "Mapping": false, "Video played to 100%": 0.0, "Campaign": "JXM | 1705015 1706010 1707028 | Branding GDN - Android", "Cost": 108.21, "Clicks": 6654, "Advertising Sub Channel": "", "Video played to 50%": 0.0, "Avg. CPV": 0.0, "View rate": 0.0, "Interactions": 6654, "Conversions": 33.0, "Campaign serving status": "eligible", "Avg. position": 1.0, "Interaction Rate": 1.44, "Campaign state": "paused", "Views": 0, "CTR": 1.44, "Avg. CPC": 0.016262, "Impressions": 462576, "End date": ""}, {"Avg. CPE": 0.0, "Account Name": "VNG - PG1 - JXM", "Start date": "2016-10-16", "Engagements": 0, "Interaction Types": ["Clicks"], "Advertising Channel": "Search", "Avg. Cost": 0.110857, "Video played to 75%": 0.0, "Date": "2017-07-16", "Avg. CPM": 18.951108, "Video played to 25%": 0.0, "Bid Strategy Type": "Target CPA", "Unique cookies": "", "Account ID": "5008396449", "Invalid clicks": 597, "Campaign ID": 682545537, "Mapping": false, "Video played to 100%": 0.0, "Campaign": "JXM | 1610105 1611013 1611026 1611062 1703048 1704016 1706008 1707026 1709039 | Search Google Play Store", "Cost": 384.12, "Clicks": 3465, "Advertising Sub Channel": "Search Mobile App", "Video played to 50%": 0.0, "Avg. CPV": 0.0, "View rate": 0.0, "Interactions": 3465, "Conversions": 1157.0, "Campaign serving status": "eligible", "Avg. position": 1.3, "Interaction Rate": 17.1, "Campaign state": "enabled", "Views": 0, "CTR": 17.1, "Avg. CPC": 0.110857, "Impressions": 20269, "End date": ""}, {"Avg. CPE": 0.010169, "Account Name": "VNG - PG1 - JXM", "Start date": "", "Engagements": 28230, "Interaction Types": "", "Advertising Channel": "", "Avg. Cost": 0.021399, "Video played to 75%": 10.78, "Date": "2017-07-16", "Avg. CPM": 0.800099, "Video played to 25%": 26.02, "Bid Strategy Type": "", "Unique cookies": "", "Account ID": "5008396449", "Invalid clicks": 3371, "Campaign ID": "", "Mapping": false, "Video played to 100%": 8.56, "Campaign": "", "Cost": 1352.68483, "Clicks": 27787, "Advertising Sub Channel": "", "Video played to 50%": 13.99, "Avg. CPV": 0.013726, "View rate": 15.05, "Interactions": 63212, "Conversions": 2674.0, "Campaign serving status": "", "Avg. position": 1.0, "Interaction Rate": 3.74, "Campaign state": "Total", "Views": 20884, "CTR": 1.64, "Avg. CPC": 0.04868, "Impressions": 1690647, "End date": ""}]