[{"Advertising Sub Channel": "", "Date": "2017-08-11", "Avg. position": 1.0, "Avg. CPM": 9.411765, "Campaign ID": 280122747, "Clicks": 4, "Campaign": "Competitor-term_Tan PhongVan", "Campaign serving status": "eligible", "Engagements": 0, "Video played to 50%": 0.0, "Invalid clicks": 1, "Avg. CPE": 0.0, "Avg. Cost": 0.04, "CTR": 23.53, "Video played to 100%": 0.0, "Unique cookies": "", "Bid Strategy Type": "cpc", "Cost": 0.16, "Views": 0, "Impressions": 17, "Avg. CPC": 0.04, "End date": "", "Avg. CPV": 0.0, "Interactions": 4, "Interaction Rate": 23.53, "Interaction Types": ["Clicks"], "Campaign state": "paused", "View rate": 0.0, "Video played to 25%": 0.0, "Video played to 75%": 0.0, "Start date": "2015-09-01", "Mapping": false, "Account ID": "1493302671", "Advertising Channel": "Search", "Conversions": 0.0}, {"Advertising Sub Channel": "", "Date": "2017-08-11", "Avg. position": 1.0, "Avg. CPM": 10.822281, "Campaign ID": 192461067, "Clicks": 158, "Campaign": "Brand-term_PhongVan", "Campaign serving status": "eligible", "Engagements": 0, "Video played to 50%": 0.0, "Invalid clicks": 9, "Avg. CPE": 0.0, "Avg. Cost": 0.051646, "CTR": 20.95, "Video played to 100%": 0.0, "Unique cookies": "", "Bid Strategy Type": "cpc", "Cost": 8.16, "Views": 0, "Impressions": 754, "Avg. CPC": 0.051646, "End date": "", "Avg. CPV": 0.0, "Interactions": 158, "Interaction Rate": 20.95, "Interaction Types": ["Clicks"], "Campaign state": "paused", "View rate": 0.0, "Video played to 25%": 0.0, "Video played to 75%": 0.0, "Start date": "2014-07-09", "Mapping": false, "Account ID": "1493302671", "Advertising Channel": "Search", "Conversions": 41.0}, {"Advertising Sub Channel": "", "Date": "2017-08-11", "Avg. position": 1.4, "Avg. CPM": 6.505102, "Campaign ID": 192460947, "Clicks": 85, "Campaign": "Brand-term_Game PhongVan", "Campaign serving status": "eligible", "Engagements": 0, "Video played to 50%": 0.0, "Invalid clicks": 8, "Avg. CPE": 0.0, "Avg. Cost": 0.03, "CTR": 21.68, "Video played to 100%": 0.0, "Unique cookies": "", "Bid Strategy Type": "cpc", "Cost": 2.55, "Views": 0, "Impressions": 392, "Avg. CPC": 0.03, "End date": "", "Avg. CPV": 0.0, "Interactions": 85, "Interaction Rate": 21.68, "Interaction Types": ["Clicks"], "Campaign state": "paused", "View rate": 0.0, "Video played to 25%": 0.0, "Video played to 75%": 0.0, "Start date": "2014-07-09", "Mapping": false, "Account ID": "1493302671", "Advertising Channel": "Search", "Conversions": 25.0}, {"Advertising Sub Channel": "", "Date": "2017-08-11", "Avg. position": 1.1, "Avg. CPM": 9.346518, "Campaign ID": "", "Clicks": 247, "Campaign": "", "Campaign serving status": "", "Engagements": 0, "Video played to 50%": 0.0, "Invalid clicks": 18, "Avg. CPE": 0.0, "Avg. Cost": 0.044008, "CTR": 21.24, "Video played to 100%": 0.0, "Unique cookies": "", "Bid Strategy Type": "", "Cost": 10.87, "Views": 0, "Impressions": 1163, "Avg. CPC": 0.044008, "End date": "", "Avg. CPV": 0.0, "Interactions": 247, "Interaction Rate": 21.24, "Interaction Types": "", "Campaign state": "Total", "View rate": 0.0, "Video played to 25%": 0.0, "Video played to 75%": 0.0, "Start date": "", "Mapping": false, "Account ID": "1493302671", "Advertising Channel": "", "Conversions": 66.0}]