[{"Conversions": 11.0, "Advertising Sub Channel": "Search Mobile App", "Interaction Rate": 2.67, "Video played to 75%": 0.0, "Avg. CPE": 0.0, "Advertising Channel": "Search", "Interactions": 36, "Invalid clicks": 7, "Unique cookies": "", "Date": "2017-08-15", "Account Name": "[M] MPI - dummy - AppInstall - - Android", "Video played to 100%": 0.0, "Campaign": "Android_CT-01_9K", "Campaign state": "enabled", "Mapping": false, "Account ID": "9411633791", "Avg. CPM": 0.890208, "Views": 0, "View rate": 0.0, "CTR": 2.67, "Video played to 50%": 0.0, "End date": "2017-10-12", "Engagements": 0, "Campaign serving status": "eligible", "Interaction Types": ["Clicks"], "Avg. CPC": 0.033333, "Video played to 25%": 0.0, "Bid Strategy Type": "cpc", "Avg. CPV": 0.0, "Cost": 1.2, "Clicks": 36, "Impressions": 1348, "Avg. position": 1.1, "Campaign ID": 811692894, "Start date": "2017-04-25", "Avg. Cost": 0.033333}, {"Conversions": 10.0, "Advertising Sub Channel": "Search Mobile App", "Interaction Rate": 9.67, "Video played to 75%": 0.0, "Avg. CPE": 0.0, "Advertising Channel": "Search", "Interactions": 47, "Invalid clicks": 12, "Unique cookies": "", "Date": "2017-08-15", "Account Name": "[M] MPI - dummy - AppInstall - - Android", "Video played to 100%": 0.0, "Campaign": "Android_CT-01_Generic_Dummy", "Campaign state": "enabled", "Mapping": false, "Account ID": "9411633791", "Avg. CPM": 5.123457, "Views": 0, "View rate": 0.0, "CTR": 9.67, "Video played to 50%": 0.0, "End date": "", "Engagements": 0, "Campaign serving status": "eligible", "Interaction Types": ["Clicks"], "Avg. CPC": 0.052979, "Video played to 25%": 0.0, "Bid Strategy Type": "cpc", "Avg. CPV": 0.0, "Cost": 2.49, "Clicks": 47, "Impressions": 486, "Avg. position": 2.4, "Campaign ID": 714787655, "Start date": "2016-12-08", "Avg. Cost": 0.052979}, {"Conversions": 1.0, "Advertising Sub Channel": "Search Mobile App", "Interaction Rate": 6.13, "Video played to 75%": 0.0, "Avg. CPE": 0.0, "Advertising Channel": "Search", "Interactions": 10, "Invalid clicks": 0, "Unique cookies": "", "Date": "2017-08-15", "Account Name": "[M] MPI - dummy - AppInstall - - Android", "Video played to 100%": 0.0, "Campaign": "Android_CT-01_Generic_GameCate", "Campaign state": "paused", "Mapping": false, "Account ID": "9411633791", "Avg. CPM": 4.233129, "Views": 0, "View rate": 0.0, "CTR": 6.13, "Video played to 50%": 0.0, "End date": "", "Engagements": 0, "Campaign serving status": "eligible", "Interaction Types": ["Clicks"], "Avg. CPC": 0.069, "Video played to 25%": 0.0, "Bid Strategy Type": "cpc", "Avg. CPV": 0.0, "Cost": 0.69, "Clicks": 10, "Impressions": 163, "Avg. position": 2.8, "Campaign ID": 777611403, "Start date": "2017-03-15", "Avg. Cost": 0.069}, {"Conversions": 0.0, "Advertising Sub Channel": "Display Mobile App", "Interaction Rate": 2.7, "Video played to 75%": 87.5, "Avg. CPE": 0.01, "Advertising Channel": "Display", "Interactions": 3, "Invalid clicks": 0, "Unique cookies": 104, "Date": "2017-08-15", "Account Name": "[M] MPI - dummy - AppInstall - - Android", "Video played to 100%": 76.92, "Campaign": "Android_CT-02_TA2-35_DE-04", "Campaign state": "paused", "Mapping": false, "Account ID": "9411633791", "Avg. CPM": 0.27027, "Views": 0, "View rate": 0.0, "CTR": 0.0, "Video played to 50%": 87.5, "End date": "", "Engagements": 3, "Campaign serving status": "eligible", "Interaction Types": ["Engagements"], "Avg. CPC": 0.0, "Video played to 25%": 89.42, "Bid Strategy Type": "Target CPA", "Avg. CPV": 0.0, "Cost": 0.03, "Clicks": 0, "Impressions": 111, "Avg. position": 1.0, "Campaign ID": 792984132, "Start date": "2017-03-30", "Avg. Cost": 0.01}, {"Conversions": 1.0, "Advertising Sub Channel": "Search Mobile App", "Interaction Rate": 5.98, "Video played to 75%": 0.0, "Avg. CPE": 0.0, "Advertising Channel": "Search", "Interactions": 7, "Invalid clicks": 0, "Unique cookies": "", "Date": "2017-08-15", "Account Name": "[M] MPI - dummy - AppInstall - - Android", "Video played to 100%": 0.0, "Campaign": "Android_CT-01_Dummy-SCT", "Campaign state": "enabled", "Mapping": false, "Account ID": "9411633791", "Avg. CPM": 4.273504, "Views": 0, "View rate": 0.0, "CTR": 5.98, "Video played to 50%": 0.0, "End date": "2017-10-12", "Engagements": 0, "Campaign serving status": "eligible", "Interaction Types": ["Clicks"], "Avg. CPC": 0.071429, "Video played to 25%": 0.0, "Bid Strategy Type": "cpc", "Avg. CPV": 0.0, "Cost": 0.5, "Clicks": 7, "Impressions": 117, "Avg. position": 2.8, "Campaign ID": 808188401, "Start date": "2017-04-20", "Avg. Cost": 0.071429}, {"Conversions": 3.0, "Advertising Sub Channel": "Search Mobile App", "Interaction Rate": 7.67, "Video played to 75%": 0.0, "Avg. CPE": 0.0, "Advertising Channel": "Search", "Interactions": 23, "Invalid clicks": 6, "Unique cookies": "", "Date": "2017-08-15", "Account Name": "[M] MPI - dummy - AppInstall - - Android", "Video played to 100%": 0.0, "Campaign": "Android_CT-01_Dummy-Tach", "Campaign state": "enabled", "Mapping": false, "Account ID": "9411633791", "Avg. CPM": 4.133333, "Views": 0, "View rate": 0.0, "CTR": 7.67, "Video played to 50%": 0.0, "End date": "", "Engagements": 0, "Campaign serving status": "eligible", "Interaction Types": ["Clicks"], "Avg. CPC": 0.053913, "Video played to 25%": 0.0, "Bid Strategy Type": "cpc", "Avg. CPV": 0.0, "Cost": 1.24, "Clicks": 23, "Impressions": 300, "Avg. position": 2.7, "Campaign ID": 808189409, "Start date": "2017-04-20", "Avg. Cost": 0.053913}, {"Conversions": 640.0, "Advertising Sub Channel": "Universal App Campaign", "Interaction Rate": 2.02, "Video played to 75%": 17.12, "Avg. CPE": 0.011406, "Advertising Channel": "Multi Channel", "Interactions": 7319, "Invalid clicks": 2117, "Unique cookies": "", "Date": "2017-08-15", "Account Name": "[M] MPI - dummy - AppInstall - - Android", "Video played to 100%": 12.65, "Campaign": "Android_CT-08_TA0-02_DE-04", "Campaign state": "paused", "Mapping": false, "Account ID": "9411633791", "Avg. CPM": 0.719938, "Views": 0, "View rate": 0.0, "CTR": 1.92, "Video played to 50%": 22.12, "End date": "", "Engagements": 377, "Campaign serving status": "eligible", "Interaction Types": ["Clicks", "Engag"], "Avg. CPC": 0.037431, "Video played to 25%": 49.97, "Bid Strategy Type": "Target CPA", "Avg. CPV": 0.0, "Cost": 260.22, "Clicks": 6952, "Impressions": 361448, "Avg. position": 1.2, "Campaign ID": 702184007, "Start date": "2016-11-18", "Avg. Cost": 0.035554}, {"Conversions": 0.0, "Advertising Sub Channel": "Search Mobile App", "Interaction Rate": 6.15, "Video played to 75%": 0.0, "Avg. CPE": 0.0, "Advertising Channel": "Search", "Interactions": 4, "Invalid clicks": 1, "Unique cookies": "", "Date": "2017-08-15", "Account Name": "[M] MPI - dummy - AppInstall - - Android", "Video played to 100%": 0.0, "Campaign": "Android_CT-01_Dummy-EN", "Campaign state": "paused", "Mapping": false, "Account ID": "9411633791", "Avg. CPM": 1.846154, "Views": 0, "View rate": 0.0, "CTR": 6.15, "Video played to 50%": 0.0, "End date": "", "Engagements": 0, "Campaign serving status": "eligible", "Interaction Types": ["Clicks"], "Avg. CPC": 0.03, "Video played to 25%": 0.0, "Bid Strategy Type": "cpc", "Avg. CPV": 0.0, "Cost": 0.12, "Clicks": 4, "Impressions": 65, "Avg. position": 1.8, "Campaign ID": 755755660, "Start date": "2017-02-15", "Avg. Cost": 0.03}, {"Conversions": 108.0, "Advertising Sub Channel": "Search Mobile App", "Interaction Rate": 8.93, "Video played to 75%": 0.0, "Avg. CPE": 0.0, "Advertising Channel": "Search", "Interactions": 431, "Invalid clicks": 16, "Unique cookies": "", "Date": "2017-08-15", "Account Name": "[M] MPI - dummy - AppInstall - - Android", "Video played to 100%": 0.0, "Campaign": "Android_CT-01_Hilo", "Campaign state": "enabled", "Mapping": false, "Account ID": "9411633791", "Avg. CPM": 7.964767, "Views": 0, "View rate": 0.0, "CTR": 8.93, "Video played to 50%": 0.0, "End date": "", "Engagements": 0, "Campaign serving status": "eligible", "Interaction Types": ["Clicks"], "Avg. CPC": 0.089165, "Video played to 25%": 0.0, "Bid Strategy Type": "cpc", "Avg. CPV": 0.0, "Cost": 38.43, "Clicks": 431, "Impressions": 4825, "Avg. position": 1.0, "Campaign ID": 808469262, "Start date": "2017-04-20", "Avg. Cost": 0.089165}, {"Conversions": 774.0, "Advertising Sub Channel": "", "Interaction Rate": 2.14, "Video played to 75%": 17.2, "Avg. CPE": 0.011395, "Advertising Channel": "", "Interactions": 7880, "Invalid clicks": 2159, "Unique cookies": "", "Date": "2017-08-15", "Account Name": "[M] MPI - dummy - AppInstall - - Android", "Video played to 100%": 12.73, "Campaign": "", "Campaign state": "Total", "Mapping": false, "Account ID": "9411633791", "Avg. CPM": 0.826648, "Views": 0, "View rate": 0.0, "CTR": 2.04, "Video played to 50%": 22.2, "End date": "", "Engagements": 380, "Campaign serving status": "", "Interaction Types": "", "Avg. CPC": 0.040602, "Video played to 25%": 50.02, "Bid Strategy Type": "", "Avg. CPV": 0.0, "Cost": 304.92, "Clicks": 7510, "Impressions": 368863, "Avg. position": 1.2, "Campaign ID": "", "Start date": "", "Avg. Cost": 0.038695}]